tempus/__init_.py
tempus/constant.py
tempus/main.py
tempus/utils.py
tempus/commands/__init__.py
tempus/commands/test.py
tempus/commands/timer.py
tempus-1.1.0.dist-info/DESCRIPTION.rst
tempus-1.1.0.dist-info/METADATA
tempus-1.1.0.dist-info/RECORD
tempus-1.1.0.dist-info/WHEEL
tempus-1.1.0.dist-info/entry_points.txt
tempus-1.1.0.dist-info/metadata.json
tempus-1.1.0.dist-info/top_level.txt
